DESCRIPTION
LICENCE
LICENSE.md
MANIFEST.in
README.md
pyproject.toml
setup.py
humanleague/__init__.py
humanleague/__init__.pyi
humanleague/py.typed
humanleague/utils.py
humanleague.egg-info/PKG-INFO
humanleague.egg-info/SOURCES.txt
humanleague.egg-info/dependency_links.txt
humanleague.egg-info/not-zip-safe
humanleague.egg-info/requires.txt
humanleague.egg-info/top_level.txt
src/DDWR.h
src/Global.h
src/IPF.h
src/Index.cpp
src/Index.h
src/Integerise.cpp
src/Integerise.h
src/Log.h
src/Microsynthesis.h
src/NDArray.h
src/NDArrayUtils.h
src/QIS.cpp
src/QIS.h
src/QISI.cpp
src/QISI.h
src/RcppExports.cpp
src/Sobol.cpp
src/Sobol.h
src/SobolData.h
src/SobolImpl.cpp
src/SobolImpl.h
src/StatFuncs.cpp
src/StatFuncs.h
src/TestIndex.cpp
src/TestNDArray.cpp
src/TestReduce.cpp
src/TestSlice.cpp
src/TestSobol.cpp
src/TestStatFuncs.cpp
src/UnitTester.cpp
src/UnitTester.h
src/docstr.inl
src/module.cpp
src/rcpp_api.cpp
tests/test_all.py
tests/test_errors.py
tests/test_utils.py