Metadata-Version: 2.4
Name: humanleague
Version: 2.4.3
Summary: Microsynthesis using quasirandom sampling and/or IPF
Author-email: Andrew Smith <andrew@friarswood.net>
Classifier: Programming Language :: Python :: 3.12
Classifier: Programming Language :: Python :: 3.13
Classifier: Programming Language :: Python :: 3.14
Classifier: Operating System :: OS Independent
Requires-Python: >=3.11
License-File: LICENCE
License-File: LICENSE.md
Requires-Dist: numpy>=2.2.2
Requires-Dist: pandas>=2.2.3
Requires-Dist: pandas-stubs>=2.2.3.250308
Dynamic: license-file
